bilicache/__init__.py
bilicache/__main__.py
bilicache/app.py
bilicache/cli.py
bilicache/api/__init__.py
bilicache/api/controller.py
bilicache/common/__init__.py
bilicache/common/check.py
bilicache/common/exceptions.py
bilicache/common/log.py
bilicache/common/network.py
bilicache/config/__init__.py
bilicache/config/cookies_locator.py
bilicache/config/ffmpeg_locator.py
bilicache/core/__init__.py
bilicache/core/download.py
bilicache/managers/__init__.py
bilicache/managers/config_manager.py
bilicache/managers/creator_manager.py
bilicache/managers/record_manager.py
bilicache-0.1.5.dist-info/licenses/LICENSE
bilicache-0.1.5.dist-info/METADATA
bilicache-0.1.5.dist-info/WHEEL
bilicache-0.1.5.dist-info/entry_points.txt
bilicache-0.1.5.dist-info/top_level.txt
bilicache-0.1.5.dist-info/RECORD
