Metadata-Version: 2.4
Name: bilicache
Version: 0.1.5
Summary: B站视频自动下载缓存工具
Author-email: hhxki <hhxki@qq.com>
License: MIT
Classifier: Development Status :: 4 - Beta
Classifier: Intended Audience :: Developers
Classifier: Topic :: Internet
Classifier: Topic :: Multimedia :: Video
Classifier: License :: OSI Approved :: MIT License
Classifier: Programming Language :: Python :: 3
Classifier: Programming Language :: Python :: 3.9
Classifier: Programming Language :: Python :: 3.10
Classifier: Programming Language :: Python :: 3.11
Requires-Python: >=3.9
License-File: LICENSE
Requires-Dist: bilibili-api-python>=5.0.0
Requires-Dist: aiohttp<3.8.0,>=3.7.4
Requires-Dist: tomlkit>=0.12.0
Requires-Dist: segno>=1.6.0
Provides-Extra: dev
Requires-Dist: pytest>=7.0.0; extra == "dev"
Requires-Dist: black>=22.0.0; extra == "dev"
Requires-Dist: flake8>=4.0.0; extra == "dev"
Dynamic: license-file
